XlsImage/MSODrawingGroup.py
XlsImage/XlsImage.py
XlsImage/__init__.py
XlsImage/__main__.py
xlsimage-0.0.2.dist-info/METADATA
xlsimage-0.0.2.dist-info/WHEEL
xlsimage-0.0.2.dist-info/licenses/LICENSE
xlsimage-0.0.2.dist-info/RECORD
