Metadata-Version: 2.1
Name: XlsImage
Version: 0.0.2
Summary: A small package for extract images from .xls files
Project-URL: Homepage, https://github.com/abumpkin/XlsImage
Project-URL: Bug Tracker, https://github.com/abumpkin/XlsImage/issues
Author-email: abumpkin <forwardslash@foxmail.com>
License-File: LICENSE
Classifier: License :: OSI Approved :: GNU General Public License v3 (GPLv3)
Classifier: Operating System :: OS Independent
Classifier: Programming Language :: Python :: 3
Requires-Python: >=3.7
